odoo10_addon_stock_split_picking-10.0.2.0.0.99.dev6-py3.8-nspkg.pth
odoo/addons/stock_split_picking/README.rst
odoo/addons/stock_split_picking/__init__.py
odoo/addons/stock_split_picking/__manifest__.py
odoo/addons/stock_split_picking/i18n/ca.po
odoo/addons/stock_split_picking/i18n/de.po
odoo/addons/stock_split_picking/i18n/es.po
odoo/addons/stock_split_picking/i18n/es_MX.po
odoo/addons/stock_split_picking/i18n/fi.po
odoo/addons/stock_split_picking/i18n/fr.po
odoo/addons/stock_split_picking/i18n/hr.po
odoo/addons/stock_split_picking/i18n/it.po
odoo/addons/stock_split_picking/i18n/nl_NL.po
odoo/addons/stock_split_picking/i18n/pt.po
odoo/addons/stock_split_picking/i18n/pt_BR.po
odoo/addons/stock_split_picking/i18n/sl.po
odoo/addons/stock_split_picking/i18n/stock_split_picking.pot
odoo/addons/stock_split_picking/i18n/tr.po
odoo/addons/stock_split_picking/i18n/tr_TR.po
odoo/addons/stock_split_picking/models/__init__.py
odoo/addons/stock_split_picking/models/stock_picking.py
odoo/addons/stock_split_picking/static/description/icon.png
odoo/addons/stock_split_picking/tests/__init__.py
odoo/addons/stock_split_picking/tests/test_stock_split_picking.py
odoo/addons/stock_split_picking/views/stock_partial_picking.xml
odoo/addons/stock_split_picking/wizards/__init__.py
odoo/addons/stock_split_picking/wizards/stock_picking_split.py
odoo/addons/stock_split_picking/wizards/stock_picking_split.xml
odoo10_addon_stock_split_picking-10.0.2.0.0.99.dev6.dist-info/METADATA
odoo10_addon_stock_split_picking-10.0.2.0.0.99.dev6.dist-info/WHEEL
odoo10_addon_stock_split_picking-10.0.2.0.0.99.dev6.dist-info/namespace_packages.txt
odoo10_addon_stock_split_picking-10.0.2.0.0.99.dev6.dist-info/top_level.txt
odoo10_addon_stock_split_picking-10.0.2.0.0.99.dev6.dist-info/RECORD
